eventcounter/__init__.py
eventcounter/eventcounter.py
eventcounter/py.typed
eventcounter-0.4.4.dist-info/METADATA
eventcounter-0.4.4.dist-info/WHEEL
eventcounter-0.4.4.dist-info/licenses/LICENSE
eventcounter-0.4.4.dist-info/RECORD
